nostrfastr/__init__.py
nostrfastr/_modidx.py
nostrfastr/client.py
nostrfastr/nostr.py
nostrfastr/notifyr.py
nostrfastr/vanity.py
nostrfastr-0.0.6.dist-info/LICENSE
nostrfastr-0.0.6.dist-info/METADATA
nostrfastr-0.0.6.dist-info/WHEEL
nostrfastr-0.0.6.dist-info/entry_points.txt
nostrfastr-0.0.6.dist-info/top_level.txt
nostrfastr-0.0.6.dist-info/RECORD
