Metadata-Version: 2.1
Name: nostrfastr
Version: 0.0.6
Summary: Getting users into nostr, fastr. A basic nostr `Client` class built in the nbdev (fast) framework to get people started nostr.
Home-page: https://github.com/armstrys/nostrfastr
Author: Ryan Armstrong
Author-email: ryscar13@gmail.com
License: MIT License
Keywords: nostr nbdev jupyter notebook python
Classifier: Development Status :: 4 - Beta
Classifier: Intended Audience :: Developers
Classifier: Natural Language :: English
Classifier: Programming Language :: Python :: 3.7
Classifier: Programming Language :: Python :: 3.8
Classifier: Programming Language :: Python :: 3.9
Classifier: Programming Language :: Python :: 3.10
Classifier: License :: OSI Approved :: MIT License
Requires-Python: >=3.7
License-File: LICENSE
Requires-Dist: nostr
Requires-Dist: appdirs
Requires-Dist: pandas
Requires-Dist: keyring
Requires-Dist: fastcore
Provides-Extra: dev
Requires-Dist: notebook ; extra == 'dev'
Requires-Dist: nostr-relay ; extra == 'dev'
